usfx/__init__.py
usfx/__main__.py
usfx/cli.py
usfx/config.py
usfx/engine.py
usfx/orchestrator.py
usfx/data/__init__.py
usfx/data/wordlist.txt
usfx/data/wordlist_large.txt
usfx/data/wordlist_small.txt
usfx/modules/__init__.py
usfx/modules/base.py
usfx/modules/cname_chaser.py
usfx/modules/dns_bruteforce.py
usfx/modules/dns_records.py
usfx/modules/dnssec_walker.py
usfx/modules/permutation.py
usfx/modules/recursive_enum.py
usfx/modules/reverse_dns.py
usfx/modules/takeover.py
usfx/modules/tls_analyzer.py
usfx/modules/vhost_scanner.py
usfx/modules/web_tech.py
usfx/modules/zone_transfer.py
usfx/utils/__init__.py
usfx/utils/dns_resolver.py
usfx/utils/output.py
usfx/utils/validator.py
usfx/utils/wildcard.py
usfx/utils/wordlist.py
usfx-1.2.1.dist-info/METADATA
usfx-1.2.1.dist-info/WHEEL
usfx-1.2.1.dist-info/entry_points.txt
usfx-1.2.1.dist-info/licenses/LICENSE
usfx-1.2.1.dist-info/RECORD
