Metadata-Version: 2.4
Name: usfx
Version: 1.2.1
Summary: USFX - Ultimate Subdomain Finder X - Discover subdomains via custom DNS servers
Project-URL: Homepage, https://github.com/nextvt/usfx
Project-URL: Repository, https://github.com/nextvt/usfx
Author: LACRYMARIA Team
License-Expression: MIT
License-File: LICENSE
Keywords: dns,enumeration,pentest,reconnaissance,security,subdomain
Classifier: Development Status :: 4 - Beta
Classifier: Environment :: Console
Classifier: Intended Audience :: Information Technology
Classifier: Intended Audience :: System Administrators
Classifier: License :: OSI Approved :: MIT License
Classifier: Operating System :: OS Independent
Classifier: Programming Language :: Python :: 3
Classifier: Programming Language :: Python :: 3.10
Classifier: Programming Language :: Python :: 3.11
Classifier: Programming Language :: Python :: 3.12
Classifier: Topic :: Security
Classifier: Topic :: System :: Networking
Requires-Python: >=3.10
Requires-Dist: click>=8.1.0
Requires-Dist: cryptography>=41.0.0
Requires-Dist: dnspython>=2.4.0
Requires-Dist: requests>=2.28.0
Requires-Dist: rich>=13.0.0
Provides-Extra: dev
Requires-Dist: black>=23.0.0; extra == 'dev'
Requires-Dist: pytest-cov>=4.0.0; extra == 'dev'
Requires-Dist: pytest>=7.0.0; extra == 'dev'
Requires-Dist: ruff>=0.1.0; extra == 'dev'
Provides-Extra: webtech
Requires-Dist: python-wappalyzer>=0.3.1; extra == 'webtech'
Requires-Dist: setuptools>=65.0.0; extra == 'webtech'
